aicli100/__init__.py
aicli100/ai.py
aicli100/cli.py
aicli100/main.py
aicli100/post_install.py
aicli100/setup.py
aicli100-1.1.1.data/data/share/aicli100/post_install.py
aicli100-1.1.1.dist-info/METADATA
aicli100-1.1.1.dist-info/WHEEL
aicli100-1.1.1.dist-info/entry_points.txt
aicli100-1.1.1.dist-info/licenses/LICENSE
aicli100-1.1.1.dist-info/RECORD
