Metadata-Version: 2.3
Name: aicli100
Version: 1.1.1
Summary: A CLI to use AI directly from the Terminal.
Project-URL: Homepage, https://github.com/roberto-fernandino/aicli_project
Author-email: Roberto Fernandino <romfernandino@gmail.com>
License-File: LICENSE
Classifier: License :: OSI Approved :: MIT License
Classifier: Operating System :: OS Independent
Classifier: Programming Language :: Python :: 3
Classifier: Topic :: Software Development :: Libraries :: Python Modules
Requires-Python: >=3.8
Requires-Dist: aiohttp
Requires-Dist: anyio
Requires-Dist: configparser
Requires-Dist: distro
Requires-Dist: httpx
Requires-Dist: openai
Requires-Dist: requests
